pystove/__init__.py
pystove/pystove.py
pystove/version.py
pystove-0.3a1.dist-info/LICENSE
pystove-0.3a1.dist-info/METADATA
pystove-0.3a1.dist-info/WHEEL
pystove-0.3a1.dist-info/top_level.txt
pystove-0.3a1.dist-info/RECORD
