Metadata-Version: 2.1
Name: pystove
Version: 0.3a1
Summary: A library to interface with HWAM wood burning stoves.
Home-page: https://github.com/mvn23/pystove
Author: Milan van Nugteren
Author-email: milan@network23.nl
License: GPLv3+
Keywords: stove hwam smartcontrol
Classifier: Development Status :: 3 - Alpha
Classifier: Topic :: Software Development :: Libraries
Classifier: License :: OSI Approved :: GNU General Public License v3 or later (GPLv3+)
License-File: LICENSE
Requires-Dist: aiohttp
